__init__.py
decorators.py
errors.py
reqparse.py
serializer.py
setup.py
flask_toolbox.egg-info/PKG-INFO
flask_toolbox.egg-info/SOURCES.txt
flask_toolbox.egg-info/dependency_links.txt
flask_toolbox.egg-info/not-zip-safe
flask_toolbox.egg-info/requires.txt
flask_toolbox.egg-info/top_level.txt