Metadata-Version: 1.0
Name: flask-toolbox
Version: 0.0.2
Summary: A flask toolbox.
Home-page: https://github.com/TuuZed/flask_toolbox
Author: TuuZed
Author-email: liuyonghui.job@gmail.com
License: Apache License 2.0
Platform: UNKNOWN
